local_brain/__init__.py
local_brain/cli.py
local_brain/models.py
local_brain/security.py
local_brain/smolagent.py
local_brain/tracing.py
local_brain-0.7.2.dist-info/METADATA
local_brain-0.7.2.dist-info/WHEEL
local_brain-0.7.2.dist-info/entry_points.txt
local_brain-0.7.2.dist-info/licenses/LICENSE
local_brain-0.7.2.dist-info/RECORD
