Metadata-Version: 2.4
Name: local-brain
Version: 0.7.2
Summary: Chat with local Ollama models that can explore your codebase
Project-URL: Homepage, https://github.com/IsmaelMartinez/local-brain
Project-URL: Repository, https://github.com/IsmaelMartinez/local-brain
Project-URL: Documentation, https://github.com/IsmaelMartinez/local-brain#readme
Author-email: Ismael Martinez <ismaelmartinez@gmail.com>
License: MIT
License-File: LICENSE
Keywords: ai,cli,llm,ollama,smolagents,tool-calling
Classifier: Development Status :: 4 - Beta
Classifier: Environment :: Console
Classifier: Intended Audience :: Developers
Classifier: License :: OSI Approved :: MIT License
Classifier: Programming Language :: Python :: 3
Classifier: Programming Language :: Python :: 3.10
Classifier: Programming Language :: Python :: 3.11
Classifier: Programming Language :: Python :: 3.12
Classifier: Programming Language :: Python :: 3.13
Classifier: Topic :: Software Development :: Quality Assurance
Requires-Python: <3.14,>=3.10
Requires-Dist: click>=8.0.0
Requires-Dist: grep-ast>=0.9.0
Requires-Dist: grpcio<1.68.0,>=1.67.0
Requires-Dist: litellm>=1.0.0
Requires-Dist: ollama>=0.6.1
Requires-Dist: smolagents>=1.0.0
Requires-Dist: tree-sitter-language-pack>=0.13.0
Requires-Dist: tree-sitter>=0.25.0
Provides-Extra: dev
Requires-Dist: mypy>=1.0.0; extra == 'dev'
Requires-Dist: pytest-cov>=4.0.0; extra == 'dev'
Requires-Dist: pytest>=7.0.0; extra == 'dev'
Requires-Dist: ruff>=0.1.0; extra == 'dev'
Provides-Extra: tracing
Requires-Dist: openinference-instrumentation-smolagents>=0.1.20; extra == 'tracing'
Requires-Dist: opentelemetry-sdk>=1.39.0; extra == 'tracing'
